CHANGES.txt
LICENSE.txt
MANIFEST.in
README.rst
ez_setup.py
setup.py
./diary/__init__.py
./diary/admin.py
./diary/backends.py
./diary/forms.py
./diary/models.py
./diary/settings.py
./diary/tests.py
./diary/urls.py
./diary/views.py
./diary/widgets.py
./diary/formats/__init__.py
./diary/formats/en/__init__.py
./diary/formats/en/formats.py
./diary/management/__init__.py
./diary/management/commands/__init__.py
./diary/management/commands/clean_entries.py
./diary/management/commands/email_reminder.py
./diary/migrations/0001_initial.py
./diary/migrations/0002_auto_20151010_1324.py
./diary/migrations/0003_auto_20151010_1331.py
./diary/migrations/0004_customer_title.py
./diary/migrations/0005_auto_20151017_1119.py
./diary/migrations/0006_auto_20151017_1347.py
./diary/migrations/0007_auto_20151017_1348.py
./diary/migrations/0008_customer_opt_out_entry_change_email_and_more.py
./diary/migrations/0009_resource_bg_color_resource_fg_color.py
./diary/migrations/0010_resource_enabled_alter_resource_bg_color_and_more.py
./diary/migrations/__init__.py
./diary/static/ajax_csrf.js
./diary/static/js.cookie.js
./diary/static/diary/base.css
./diary/static/diary/entry_ajax_dnd.js
./diary/static/diary/entry_ajax_modal.js
./diary/static/diary/multi_col.css
./diary/templates/diary/base.html
./diary/templates/diary/customer_add.html
./diary/templates/diary/customer_change.html
./diary/templates/diary/day.html
./diary/templates/diary/day_base.html
./diary/templates/diary/day_list.html
./diary/templates/diary/email_notify_entry_change.txt
./diary/templates/diary/email_notify_entry_status_change.txt
./diary/templates/diary/email_notify_new_entry.txt
./diary/templates/diary/email_reminder.txt
./diary/templates/diary/entry.html
./diary/templates/diary/form_base.html
./diary/templates/diary/history.html
./diary/templates/diary/main_base.html
./diary/templates/diary/modal_base.html
./diary/templates/diary/modal_entry.html
./diary/templates/diary/month.html
./diary/templates/diary/multi_day.html
django_diary.egg-info/PKG-INFO
django_diary.egg-info/SOURCES.txt
django_diary.egg-info/dependency_links.txt
django_diary.egg-info/not-zip-safe
django_diary.egg-info/requires.txt
django_diary.egg-info/top_level.txt