Metadata-Version: 2.1
Name: django-diary
Version: 4.2.17
Summary: A pluggable diary app for use in the Django framework.
Home-page: http://pypi.python.org/pypi/django-diary/
Author: Bob Bowles
Author-email: bobjohnbowles@gmail.com
License: MIT License
Keywords: Diary,Django
Classifier: Programming Language :: Python
Classifier: Programming Language :: Python :: 3
Classifier: Programming Language :: Python :: 3.12
Classifier: Development Status :: 3 - Alpha
Classifier: Environment :: Web Environment
Classifier: Framework :: Django :: 4.2
Classifier: Intended Audience :: Developers
Classifier: License :: OSI Approved :: MIT License
Classifier: Operating System :: POSIX :: Linux
Classifier: Topic :: Internet :: WWW/HTTP
Classifier: Topic :: Internet :: WWW/HTTP :: Dynamic Content
Classifier: Topic :: Internet :: WWW/HTTP :: Dynamic Content :: News/Diary
Classifier: Topic :: Utilities
License-File: LICENSE.txt
Requires-Dist: Django<5,~=4.2.17
Requires-Dist: django-datetime-widget2>=0.9.5
Requires-Dist: DateTime>=5.2
